Metadata-Version: 2.1
Name: clarmy02
Version: 0.0.4
Summary: example
Home-page: https://github.com/Clarmy/clarmy02
Author: Wentao Li
Author-email: 
Classifier: Programming Language :: Python :: 3
Requires-Python: >=3.8
License-File: LICENSE
